LICENSE
MANIFEST.in
README.md
setup.py
chocloton/__init__.py
chocloton/choclo_backend.py
chocloton/choclo_optimizer.py
chocloton/choclo_parameter_search.py
chocloton.egg-info/PKG-INFO
chocloton.egg-info/SOURCES.txt
chocloton.egg-info/dependency_links.txt
chocloton.egg-info/requires.txt
chocloton.egg-info/top_level.txt
chocloton/helpers/__init__.py
chocloton/helpers/heapsort.py